Classfile /C:/Users/669/Desktop/637d4be4f2a5440089c0c51610363867/275-jvm-test/src/test/SimpleArrayTest/SimpleArr.class
  Last modified Jul 8, 2020; size 285 bytes
  MD5 checksum 0a08ee19baf47b51622a8301da5b60a1
  Compiled from "SimpleArr.java"
public class SimpleArr
  minor version: 0
  major version: 52
  flags: ACC_PUBLIC, ACC_SUPER
Constant pool:
   #1 = Methodref          #4.#13         // java/lang/Object."<init>":()V
   #2 = Class              #14            // "[[[I"
   #3 = Class              #15            // SimpleArr
   #4 = Class              #16            // java/lang/Object
   #5 = Utf8               <init>
   #6 = Utf8               ()V
   #7 = Utf8               Code
   #8 = Utf8               LineNumberTable
   #9 = Utf8               main
  #10 = Utf8               ([Ljava/lang/String;)V
  #11 = Utf8               SourceFile
  #12 = Utf8               SimpleArr.java
  #13 = NameAndType        #5:#6          // "<init>":()V
  #14 = Utf8               [[[I
  #15 = Utf8               SimpleArr
  #16 = Utf8               java/lang/Object
{
  public SimpleArr();
    descriptor: ()V
    flags: ACC_PUBLIC
    Code:
      stack=1, locals=1, args_size=1
         0: aload_0
         1: invokespecial #1                  // Method java/lang/Object."<init>":()V
         4: return
      LineNumberTable:
        line 1: 0

  public static void main(java.lang.String[]);
    descriptor: ([Ljava/lang/String;)V
    flags: ACC_PUBLIC, ACC_STATIC
    Code:
      stack=3, locals=2, args_size=1
         0: iconst_3
         1: iconst_4
         2: iconst_5
         3: multianewarray #2,  3             // class "[[[I"
         7: astore_1
         8: return
      LineNumberTable:
        line 4: 0
        line 5: 8
}
SourceFile: "SimpleArr.java"
